{"name":"Ejemplo1.1","id":"ejemplo;ejemplo1.1","testSteps":[{"number":1,"description":"Given that Cris go to page","duration":35135,"startTime":"2023-03-14T16:00:30.760-04:00[America/New_York]","screenshots":[{"screenshot":"cdcbd63ac88a2d7b4ae011c7ead5fc28b62e7a6739338cecde711431363fd8d4.png","timeStamp":1678824065895}],"result":"SUCCESS","precondition":false,"level":0,"children":[{"number":2,"description":"Actor go to","duration":29631,"startTime":"2023-03-14T16:00:31.496-04:00[America/New_York]","screenshots":[{"screenshot":"f33d5b1227180fd777c0535ea571a41ff74fe4ead20b08cfc3530f843598050b.png","timeStamp":1678824061127}],"result":"SUCCESS","precondition":false,"level":1,"children":[{"number":3,"description":"actor opens the https://www.koaj.co/","duration":23636,"startTime":"2023-03-14T16:00:31.524-04:00[America/New_York]","screenshots":[{"screenshot":"f3dab09a05a7dbe9ecccb32418aa5bbd19b46e2ebc4fa6e712e42e5f669d1575.png","timeStamp":1678824055159}],"result":"SUCCESS","precondition":false,"level":2}]}]},{"number":4,"description":"When Cris using the credentials on register \"trishtan142@gmail.com\" \"1073177637C\"","duration":16235,"startTime":"2023-03-14T16:01:05.899-04:00[America/New_York]","screenshots":[{"screenshot":"0545020ea373740b5154d14707c7b3b21b6cf807a8931a9ca6ba1f35722a187f.png","timeStamp":1678824082134}],"result":"SUCCESS","precondition":false,"level":0,"children":[{"number":5,"description":"Actor iniciar","duration":16169,"startTime":"2023-03-14T16:01:05.953-04:00[America/New_York]","screenshots":[{"screenshot":"0545020ea373740b5154d14707c7b3b21b6cf807a8931a9ca6ba1f35722a187f.png","timeStamp":1678824082122}],"result":"SUCCESS","precondition":false,"level":1,"children":[{"number":6,"description":"actor clicks on By.cssSelector: .flex .login","duration":10600,"startTime":"2023-03-14T16:01:06.577-04:00[America/New_York]","screenshots":[{"screenshot":"796349859826de376c8a34eed671db6baefde977de45e00c6e4b8051a1cfd1a7.png","timeStamp":1678824077177}],"result":"SUCCESS","precondition":false,"level":2},{"number":7,"description":"actor enters \u0027trishtan142@gmail.com\u0027 into User","duration":2684,"startTime":"2023-03-14T16:01:17.623-04:00[America/New_York]","screenshots":[{"screenshot":"911a949ac7dce2bf860317dadafadf14cb0540b0cddd8ab5a1e0a54134f14d6a.png","timeStamp":1678824080307}],"result":"SUCCESS","precondition":false,"level":2},{"number":8,"description":"actor enters \u00271073177637C\u0027 into Pass","duration":1796,"startTime":"2023-03-14T16:01:20.310-04:00[America/New_York]","screenshots":[{"screenshot":"0545020ea373740b5154d14707c7b3b21b6cf807a8931a9ca6ba1f35722a187f.png","timeStamp":1678824082106}],"result":"SUCCESS","precondition":false,"level":2}]}]},{"number":9,"description":"Then Cris see the homepage","duration":13,"startTime":"2023-03-14T16:01:22.136-04:00[America/New_York]","screenshots":[{"screenshot":"0545020ea373740b5154d14707c7b3b21b6cf807a8931a9ca6ba1f35722a187f.png","timeStamp":1678824082149}],"result":"SUCCESS","precondition":false,"level":0}],"userStory":{"id":"ejemplo","storyName":"Ejemplo","path":"file:///C:/Users/jonathan.amaya/eclipse-workspace/Example2/src/test/resources/Features/FeatureEX.feature","type":"feature"},"featureTag":{"name":"Ejemplo","type":"feature","displayName":"Ejemplo"},"title":"Ejemplo1.1","description":"","tags":[{"name":"Ejemplo","type":"feature","displayName":"Ejemplo"}],"startTime":"2023-03-14T16:00:30.414-04:00[America/New_York]","duration":51740,"projectKey":"","sessionId":"fcc390c29dba93edb55ac21ae1587286","driver":"chrome:actor","isManualTestingUpToDate":false,"manual":false,"testSource":"Cucumber","actors":[{"name":"actor","can":["browse the web"]}],"result":"SUCCESS"}