{"name":"Ejemplo1.1","id":"ejemplo;ejemplo1.1","testSteps":[{"number":1,"description":"Given that Cris go to page","duration":20236,"startTime":"2023-03-14T14:40:07.785-04:00[America/New_York]","result":"SUCCESS","precondition":false,"level":0,"children":[{"number":2,"description":"Actor go to","duration":19220,"startTime":"2023-03-14T14:40:08.760-04:00[America/New_York]","result":"SUCCESS","precondition":false,"level":1,"children":[{"number":3,"description":"actor opens the https://www.koaj.co/","duration":19115,"startTime":"2023-03-14T14:40:08.810-04:00[America/New_York]","screenshots":[{"screenshot":"31654f2dae7512e4a1125513b5c2dc43105c1f768166b4af52c6bcc00a26b4f9.png","timeStamp":1678819227917}],"result":"SUCCESS","precondition":false,"level":2}]}]},{"number":4,"description":"When Cris using the credentials on register \"trishtan142@gmail.com\" \"1073177637C\"","duration":5753,"startTime":"2023-03-14T14:40:28.023-04:00[America/New_York]","exception":{"errorType":"net.thucydides.core.webdriver.exceptions.ElementShouldBePresentException","message":"Expected condition failed: waiting for By.cssSelector: .flex .login to be present (tried for 5 second(s) with 100 milliseconds interval)\nBuild info: version: \u00273.141.59\u0027, revision: \u0027e82be7d358\u0027, time: \u00272018-11-14T08:17:03\u0027\nSystem info: host: \u0027SWO059169593957\u0027, ip: \u0027192.168.68.53\u0027, os.name: \u0027Windows 10\u0027, os.arch: \u0027amd64\u0027, os.version: \u002710.0\u0027, java.version: \u00271.8.0_361\u0027\nDriver info: driver.version: unknown","stackTrace":[{"declaringClass":"org.example.Task.Iniciar","methodName":"performAs","fileName":"Iniciar.java","lineNumber":26},{"declaringClass":"org.example.stepdefinitions.StepDefinitions","methodName":"whenCrisUsingTheCredentialsOnRegister","fileName":"StepDefinitions.java","lineNumber":31},{"declaringClass":"io.cucumber.java.Invoker","methodName":"doInvoke","fileName":"Invoker.java","lineNumber":66},{"declaringClass":"io.cucumber.java.Invoker","methodName":"invoke","fileName":"Invoker.java","lineNumber":24},{"declaringClass":"io.cucumber.java.AbstractGlueDefinition","methodName":"invokeMethod","fileName":"AbstractGlueDefinition.java","lineNumber":47},{"declaringClass":"io.cucumber.java.JavaStepDefinition","methodName":"execute","fileName":"JavaStepDefinition.java","lineNumber":29},{"declaringClass":"io.cucumber.core.runner.CoreStepDefinition","methodName":"execute","fileName":"CoreStepDefinition.java","lineNumber":66},{"declaringClass":"io.cucumber.core.runner.PickleStepDefinitionMatch","methodName":"runStep","fileName":"PickleStepDefinitionMatch.java","lineNumber":63},{"declaringClass":"io.cucumber.core.runner.TestStep","methodName":"executeStep","fileName":"TestStep.java","lineNumber":92},{"declaringClass":"io.cucumber.core.runner.TestStep","methodName":"run","fileName":"TestStep.java","lineNumber":64},{"declaringClass":"io.cucumber.core.runner.PickleStepTestStep","methodName":"run","fileName":"PickleStepTestStep.java","lineNumber":51},{"declaringClass":"io.cucumber.core.runner.TestCase","methodName":"run","fileName":"TestCase.java","lineNumber":104},{"declaringClass":"io.cucumber.core.runner.Runner","methodName":"runPickle","fileName":"Runner.java","lineNumber":73},{"declaringClass":"io.cucumber.junit.FeatureRunner","methodName":"runChild","fileName":"FeatureRunner.java","lineNumber":135},{"declaringClass":"io.cucumber.junit.FeatureRunner","methodName":"runChild","fileName":"FeatureRunner.java","lineNumber":27},{"declaringClass":"io.cucumber.junit.CucumberSerenityRunner","methodName":"runChild","fileName":"CucumberSerenityRunner.java","lineNumber":235},{"declaringClass":"io.cucumber.junit.CucumberSerenityRunner","methodName":"runChild","fileName":"CucumberSerenityRunner.java","lineNumber":54},{"declaringClass":"worker.org.gradle.process.internal.worker.GradleWorkerMain","methodName":"run","fileName":"GradleWorkerMain.java","lineNumber":69},{"declaringClass":"worker.org.gradle.process.internal.worker.GradleWorkerMain","methodName":"main","fileName":"GradleWorkerMain.java","lineNumber":74}],"rootCause":{"errorType":"org.openqa.selenium.TimeoutException","message":"Expected condition failed: waiting for By.cssSelector: .flex .login to be present (tried for 5 second(s) with 100 milliseconds interval)\nBuild info: version: \u00273.141.59\u0027, revision: \u0027e82be7d358\u0027, time: \u00272018-11-14T08:17:03\u0027\nSystem info: host: \u0027SWO059169593957\u0027, ip: \u0027192.168.68.53\u0027, os.name: \u0027Windows 10\u0027, os.arch: \u0027amd64\u0027, os.version: \u002710.0\u0027, java.version: \u00271.8.0_361\u0027\nDriver info: driver.version: unknown","stackTrace":[{"declaringClass":"org.example.Task.Iniciar","methodName":"performAs","fileName":"Iniciar.java","lineNumber":26},{"declaringClass":"org.example.stepdefinitions.StepDefinitions","methodName":"whenCrisUsingTheCredentialsOnRegister","fileName":"StepDefinitions.java","lineNumber":31},{"declaringClass":"io.cucumber.java.Invoker","methodName":"doInvoke","fileName":"Invoker.java","lineNumber":66},{"declaringClass":"io.cucumber.java.Invoker","methodName":"invoke","fileName":"Invoker.java","lineNumber":24},{"declaringClass":"io.cucumber.java.AbstractGlueDefinition","methodName":"invokeMethod","fileName":"AbstractGlueDefinition.java","lineNumber":47},{"declaringClass":"io.cucumber.java.JavaStepDefinition","methodName":"execute","fileName":"JavaStepDefinition.java","lineNumber":29},{"declaringClass":"io.cucumber.core.runner.CoreStepDefinition","methodName":"execute","fileName":"CoreStepDefinition.java","lineNumber":66},{"declaringClass":"io.cucumber.core.runner.PickleStepDefinitionMatch","methodName":"runStep","fileName":"PickleStepDefinitionMatch.java","lineNumber":63},{"declaringClass":"io.cucumber.core.runner.TestStep","methodName":"executeStep","fileName":"TestStep.java","lineNumber":92},{"declaringClass":"io.cucumber.core.runner.TestStep","methodName":"run","fileName":"TestStep.java","lineNumber":64},{"declaringClass":"io.cucumber.core.runner.PickleStepTestStep","methodName":"run","fileName":"PickleStepTestStep.java","lineNumber":51},{"declaringClass":"io.cucumber.core.runner.TestCase","methodName":"run","fileName":"TestCase.java","lineNumber":104},{"declaringClass":"io.cucumber.core.runner.Runner","methodName":"runPickle","fileName":"Runner.java","lineNumber":73},{"declaringClass":"io.cucumber.junit.FeatureRunner","methodName":"runChild","fileName":"FeatureRunner.java","lineNumber":135},{"declaringClass":"io.cucumber.junit.FeatureRunner","methodName":"runChild","fileName":"FeatureRunner.java","lineNumber":27},{"declaringClass":"io.cucumber.junit.CucumberSerenityRunner","methodName":"runChild","fileName":"CucumberSerenityRunner.java","lineNumber":235},{"declaringClass":"io.cucumber.junit.CucumberSerenityRunner","methodName":"runChild","fileName":"CucumberSerenityRunner.java","lineNumber":54},{"declaringClass":"worker.org.gradle.process.internal.worker.GradleWorkerMain","methodName":"run","fileName":"GradleWorkerMain.java","lineNumber":69},{"declaringClass":"worker.org.gradle.process.internal.worker.GradleWorkerMain","methodName":"main","fileName":"GradleWorkerMain.java","lineNumber":74}]}},"result":"FAILURE","precondition":false,"level":0,"children":[{"number":5,"description":"Actor iniciar","duration":5704,"startTime":"2023-03-14T14:40:28.050-04:00[America/New_York]","exception":{"errorType":"net.thucydides.core.webdriver.exceptions.ElementShouldBePresentException","message":"Expected condition failed: waiting for By.cssSelector: .flex .login to be present (tried for 5 second(s) with 100 milliseconds interval)\nBuild info: version: \u00273.141.59\u0027, revision: \u0027e82be7d358\u0027, time: \u00272018-11-14T08:17:03\u0027\nSystem info: host: \u0027SWO059169593957\u0027, ip: \u0027192.168.68.53\u0027, os.name: \u0027Windows 10\u0027, os.arch: \u0027amd64\u0027, os.version: \u002710.0\u0027, java.version: \u00271.8.0_361\u0027\nDriver info: driver.version: unknown","stackTrace":[{"declaringClass":"org.example.Task.Iniciar","methodName":"performAs","fileName":"Iniciar.java","lineNumber":26},{"declaringClass":"org.example.stepdefinitions.StepDefinitions","methodName":"whenCrisUsingTheCredentialsOnRegister","fileName":"StepDefinitions.java","lineNumber":31},{"declaringClass":"io.cucumber.java.Invoker","methodName":"doInvoke","fileName":"Invoker.java","lineNumber":66},{"declaringClass":"io.cucumber.java.Invoker","methodName":"invoke","fileName":"Invoker.java","lineNumber":24},{"declaringClass":"io.cucumber.java.AbstractGlueDefinition","methodName":"invokeMethod","fileName":"AbstractGlueDefinition.java","lineNumber":47},{"declaringClass":"io.cucumber.java.JavaStepDefinition","methodName":"execute","fileName":"JavaStepDefinition.java","lineNumber":29},{"declaringClass":"io.cucumber.core.runner.CoreStepDefinition","methodName":"execute","fileName":"CoreStepDefinition.java","lineNumber":66},{"declaringClass":"io.cucumber.core.runner.PickleStepDefinitionMatch","methodName":"runStep","fileName":"PickleStepDefinitionMatch.java","lineNumber":63},{"declaringClass":"io.cucumber.core.runner.TestStep","methodName":"executeStep","fileName":"TestStep.java","lineNumber":92},{"declaringClass":"io.cucumber.core.runner.TestStep","methodName":"run","fileName":"TestStep.java","lineNumber":64},{"declaringClass":"io.cucumber.core.runner.PickleStepTestStep","methodName":"run","fileName":"PickleStepTestStep.java","lineNumber":51},{"declaringClass":"io.cucumber.core.runner.TestCase","methodName":"run","fileName":"TestCase.java","lineNumber":104},{"declaringClass":"io.cucumber.core.runner.Runner","methodName":"runPickle","fileName":"Runner.java","lineNumber":73},{"declaringClass":"io.cucumber.junit.FeatureRunner","methodName":"runChild","fileName":"FeatureRunner.java","lineNumber":135},{"declaringClass":"io.cucumber.junit.FeatureRunner","methodName":"runChild","fileName":"FeatureRunner.java","lineNumber":27},{"declaringClass":"io.cucumber.junit.CucumberSerenityRunner","methodName":"runChild","fileName":"CucumberSerenityRunner.java","lineNumber":235},{"declaringClass":"io.cucumber.junit.CucumberSerenityRunner","methodName":"runChild","fileName":"CucumberSerenityRunner.java","lineNumber":54},{"declaringClass":"worker.org.gradle.process.internal.worker.GradleWorkerMain","methodName":"run","fileName":"GradleWorkerMain.java","lineNumber":69},{"declaringClass":"worker.org.gradle.process.internal.worker.GradleWorkerMain","methodName":"main","fileName":"GradleWorkerMain.java","lineNumber":74}],"rootCause":{"errorType":"org.openqa.selenium.TimeoutException","message":"Expected condition failed: waiting for By.cssSelector: .flex .login to be present (tried for 5 second(s) with 100 milliseconds interval)\nBuild info: version: \u00273.141.59\u0027, revision: \u0027e82be7d358\u0027, time: \u00272018-11-14T08:17:03\u0027\nSystem info: host: \u0027SWO059169593957\u0027, ip: \u0027192.168.68.53\u0027, os.name: \u0027Windows 10\u0027, os.arch: \u0027amd64\u0027, os.version: \u002710.0\u0027, java.version: \u00271.8.0_361\u0027\nDriver info: driver.version: unknown","stackTrace":[{"declaringClass":"org.example.Task.Iniciar","methodName":"performAs","fileName":"Iniciar.java","lineNumber":26},{"declaringClass":"org.example.stepdefinitions.StepDefinitions","methodName":"whenCrisUsingTheCredentialsOnRegister","fileName":"StepDefinitions.java","lineNumber":31},{"declaringClass":"io.cucumber.java.Invoker","methodName":"doInvoke","fileName":"Invoker.java","lineNumber":66},{"declaringClass":"io.cucumber.java.Invoker","methodName":"invoke","fileName":"Invoker.java","lineNumber":24},{"declaringClass":"io.cucumber.java.AbstractGlueDefinition","methodName":"invokeMethod","fileName":"AbstractGlueDefinition.java","lineNumber":47},{"declaringClass":"io.cucumber.java.JavaStepDefinition","methodName":"execute","fileName":"JavaStepDefinition.java","lineNumber":29},{"declaringClass":"io.cucumber.core.runner.CoreStepDefinition","methodName":"execute","fileName":"CoreStepDefinition.java","lineNumber":66},{"declaringClass":"io.cucumber.core.runner.PickleStepDefinitionMatch","methodName":"runStep","fileName":"PickleStepDefinitionMatch.java","lineNumber":63},{"declaringClass":"io.cucumber.core.runner.TestStep","methodName":"executeStep","fileName":"TestStep.java","lineNumber":92},{"declaringClass":"io.cucumber.core.runner.TestStep","methodName":"run","fileName":"TestStep.java","lineNumber":64},{"declaringClass":"io.cucumber.core.runner.PickleStepTestStep","methodName":"run","fileName":"PickleStepTestStep.java","lineNumber":51},{"declaringClass":"io.cucumber.core.runner.TestCase","methodName":"run","fileName":"TestCase.java","lineNumber":104},{"declaringClass":"io.cucumber.core.runner.Runner","methodName":"runPickle","fileName":"Runner.java","lineNumber":73},{"declaringClass":"io.cucumber.junit.FeatureRunner","methodName":"runChild","fileName":"FeatureRunner.java","lineNumber":135},{"declaringClass":"io.cucumber.junit.FeatureRunner","methodName":"runChild","fileName":"FeatureRunner.java","lineNumber":27},{"declaringClass":"io.cucumber.junit.CucumberSerenityRunner","methodName":"runChild","fileName":"CucumberSerenityRunner.java","lineNumber":235},{"declaringClass":"io.cucumber.junit.CucumberSerenityRunner","methodName":"runChild","fileName":"CucumberSerenityRunner.java","lineNumber":54},{"declaringClass":"worker.org.gradle.process.internal.worker.GradleWorkerMain","methodName":"run","fileName":"GradleWorkerMain.java","lineNumber":69},{"declaringClass":"worker.org.gradle.process.internal.worker.GradleWorkerMain","methodName":"main","fileName":"GradleWorkerMain.java","lineNumber":74}]}},"result":"FAILURE","precondition":false,"level":1,"children":[{"number":6,"description":"actor clicks on By.cssSelector: .flex .login","duration":5376,"startTime":"2023-03-14T14:40:28.354-04:00[America/New_York]","exception":{"errorType":"net.thucydides.core.webdriver.exceptions.ElementShouldBePresentException","message":"Expected condition failed: waiting for By.cssSelector: .flex .login to be present (tried for 5 second(s) with 100 milliseconds interval)\nBuild info: version: \u00273.141.59\u0027, revision: \u0027e82be7d358\u0027, time: \u00272018-11-14T08:17:03\u0027\nSystem info: host: \u0027SWO059169593957\u0027, ip: \u0027192.168.68.53\u0027, os.name: \u0027Windows 10\u0027, os.arch: \u0027amd64\u0027, os.version: \u002710.0\u0027, java.version: \u00271.8.0_361\u0027\nDriver info: driver.version: unknown","stackTrace":[{"declaringClass":"org.example.Task.Iniciar","methodName":"performAs","fileName":"Iniciar.java","lineNumber":26},{"declaringClass":"org.example.stepdefinitions.StepDefinitions","methodName":"whenCrisUsingTheCredentialsOnRegister","fileName":"StepDefinitions.java","lineNumber":31},{"declaringClass":"io.cucumber.java.Invoker","methodName":"doInvoke","fileName":"Invoker.java","lineNumber":66},{"declaringClass":"io.cucumber.java.Invoker","methodName":"invoke","fileName":"Invoker.java","lineNumber":24},{"declaringClass":"io.cucumber.java.AbstractGlueDefinition","methodName":"invokeMethod","fileName":"AbstractGlueDefinition.java","lineNumber":47},{"declaringClass":"io.cucumber.java.JavaStepDefinition","methodName":"execute","fileName":"JavaStepDefinition.java","lineNumber":29},{"declaringClass":"io.cucumber.core.runner.CoreStepDefinition","methodName":"execute","fileName":"CoreStepDefinition.java","lineNumber":66},{"declaringClass":"io.cucumber.core.runner.PickleStepDefinitionMatch","methodName":"runStep","fileName":"PickleStepDefinitionMatch.java","lineNumber":63},{"declaringClass":"io.cucumber.core.runner.TestStep","methodName":"executeStep","fileName":"TestStep.java","lineNumber":92},{"declaringClass":"io.cucumber.core.runner.TestStep","methodName":"run","fileName":"TestStep.java","lineNumber":64},{"declaringClass":"io.cucumber.core.runner.PickleStepTestStep","methodName":"run","fileName":"PickleStepTestStep.java","lineNumber":51},{"declaringClass":"io.cucumber.core.runner.TestCase","methodName":"run","fileName":"TestCase.java","lineNumber":104},{"declaringClass":"io.cucumber.core.runner.Runner","methodName":"runPickle","fileName":"Runner.java","lineNumber":73},{"declaringClass":"io.cucumber.junit.FeatureRunner","methodName":"runChild","fileName":"FeatureRunner.java","lineNumber":135},{"declaringClass":"io.cucumber.junit.FeatureRunner","methodName":"runChild","fileName":"FeatureRunner.java","lineNumber":27},{"declaringClass":"io.cucumber.junit.CucumberSerenityRunner","methodName":"runChild","fileName":"CucumberSerenityRunner.java","lineNumber":235},{"declaringClass":"io.cucumber.junit.CucumberSerenityRunner","methodName":"runChild","fileName":"CucumberSerenityRunner.java","lineNumber":54},{"declaringClass":"worker.org.gradle.process.internal.worker.GradleWorkerMain","methodName":"run","fileName":"GradleWorkerMain.java","lineNumber":69},{"declaringClass":"worker.org.gradle.process.internal.worker.GradleWorkerMain","methodName":"main","fileName":"GradleWorkerMain.java","lineNumber":74}],"rootCause":{"errorType":"org.openqa.selenium.TimeoutException","message":"Expected condition failed: waiting for By.cssSelector: .flex .login to be present (tried for 5 second(s) with 100 milliseconds interval)\nBuild info: version: \u00273.141.59\u0027, revision: \u0027e82be7d358\u0027, time: \u00272018-11-14T08:17:03\u0027\nSystem info: host: \u0027SWO059169593957\u0027, ip: \u0027192.168.68.53\u0027, os.name: \u0027Windows 10\u0027, os.arch: \u0027amd64\u0027, os.version: \u002710.0\u0027, java.version: \u00271.8.0_361\u0027\nDriver info: driver.version: unknown","stackTrace":[{"declaringClass":"org.example.Task.Iniciar","methodName":"performAs","fileName":"Iniciar.java","lineNumber":26},{"declaringClass":"org.example.stepdefinitions.StepDefinitions","methodName":"whenCrisUsingTheCredentialsOnRegister","fileName":"StepDefinitions.java","lineNumber":31},{"declaringClass":"io.cucumber.java.Invoker","methodName":"doInvoke","fileName":"Invoker.java","lineNumber":66},{"declaringClass":"io.cucumber.java.Invoker","methodName":"invoke","fileName":"Invoker.java","lineNumber":24},{"declaringClass":"io.cucumber.java.AbstractGlueDefinition","methodName":"invokeMethod","fileName":"AbstractGlueDefinition.java","lineNumber":47},{"declaringClass":"io.cucumber.java.JavaStepDefinition","methodName":"execute","fileName":"JavaStepDefinition.java","lineNumber":29},{"declaringClass":"io.cucumber.core.runner.CoreStepDefinition","methodName":"execute","fileName":"CoreStepDefinition.java","lineNumber":66},{"declaringClass":"io.cucumber.core.runner.PickleStepDefinitionMatch","methodName":"runStep","fileName":"PickleStepDefinitionMatch.java","lineNumber":63},{"declaringClass":"io.cucumber.core.runner.TestStep","methodName":"executeStep","fileName":"TestStep.java","lineNumber":92},{"declaringClass":"io.cucumber.core.runner.TestStep","methodName":"run","fileName":"TestStep.java","lineNumber":64},{"declaringClass":"io.cucumber.core.runner.PickleStepTestStep","methodName":"run","fileName":"PickleStepTestStep.java","lineNumber":51},{"declaringClass":"io.cucumber.core.runner.TestCase","methodName":"run","fileName":"TestCase.java","lineNumber":104},{"declaringClass":"io.cucumber.core.runner.Runner","methodName":"runPickle","fileName":"Runner.java","lineNumber":73},{"declaringClass":"io.cucumber.junit.FeatureRunner","methodName":"runChild","fileName":"FeatureRunner.java","lineNumber":135},{"declaringClass":"io.cucumber.junit.FeatureRunner","methodName":"runChild","fileName":"FeatureRunner.java","lineNumber":27},{"declaringClass":"io.cucumber.junit.CucumberSerenityRunner","methodName":"runChild","fileName":"CucumberSerenityRunner.java","lineNumber":235},{"declaringClass":"io.cucumber.junit.CucumberSerenityRunner","methodName":"runChild","fileName":"CucumberSerenityRunner.java","lineNumber":54},{"declaringClass":"worker.org.gradle.process.internal.worker.GradleWorkerMain","methodName":"run","fileName":"GradleWorkerMain.java","lineNumber":69},{"declaringClass":"worker.org.gradle.process.internal.worker.GradleWorkerMain","methodName":"main","fileName":"GradleWorkerMain.java","lineNumber":74}]}},"result":"FAILURE","precondition":false,"level":2}]}]},{"number":7,"description":"Then Cris see the homepage","duration":9,"startTime":"2023-03-14T14:40:33.813-04:00[America/New_York]","result":"SKIPPED","precondition":false,"level":0}],"userStory":{"id":"ejemplo","storyName":"Ejemplo","path":"file:///C:/Users/jonathan.amaya/eclipse-workspace/Example2/src/test/resources/Features/FeatureEX.feature","type":"feature"},"featureTag":{"name":"Ejemplo","type":"feature","displayName":"Ejemplo"},"title":"Ejemplo1.1","description":"","tags":[{"name":"Ejemplo","type":"feature","displayName":"Ejemplo"}],"startTime":"2023-03-14T14:40:07.294-04:00[America/New_York]","duration":26544,"testFailureCause":{"errorType":"net.thucydides.core.webdriver.exceptions.ElementShouldBePresentException","message":"Expected condition failed: waiting for By.cssSelector: .flex .login to be present (tried for 5 second(s) with 100 milliseconds interval)\nBuild info: version: \u00273.141.59\u0027, revision: \u0027e82be7d358\u0027, time: \u00272018-11-14T08:17:03\u0027\nSystem info: host: \u0027SWO059169593957\u0027, ip: \u0027192.168.68.53\u0027, os.name: \u0027Windows 10\u0027, os.arch: \u0027amd64\u0027, os.version: \u002710.0\u0027, java.version: \u00271.8.0_361\u0027\nDriver info: driver.version: unknown","stackTrace":[{"declaringClass":"org.example.Task.Iniciar","methodName":"performAs","fileName":"Iniciar.java","lineNumber":26},{"declaringClass":"org.example.stepdefinitions.StepDefinitions","methodName":"whenCrisUsingTheCredentialsOnRegister","fileName":"StepDefinitions.java","lineNumber":31},{"declaringClass":"io.cucumber.java.Invoker","methodName":"doInvoke","fileName":"Invoker.java","lineNumber":66},{"declaringClass":"io.cucumber.java.Invoker","methodName":"invoke","fileName":"Invoker.java","lineNumber":24},{"declaringClass":"io.cucumber.java.AbstractGlueDefinition","methodName":"invokeMethod","fileName":"AbstractGlueDefinition.java","lineNumber":47},{"declaringClass":"io.cucumber.java.JavaStepDefinition","methodName":"execute","fileName":"JavaStepDefinition.java","lineNumber":29},{"declaringClass":"io.cucumber.core.runner.CoreStepDefinition","methodName":"execute","fileName":"CoreStepDefinition.java","lineNumber":66},{"declaringClass":"io.cucumber.core.runner.PickleStepDefinitionMatch","methodName":"runStep","fileName":"PickleStepDefinitionMatch.java","lineNumber":63},{"declaringClass":"io.cucumber.core.runner.TestStep","methodName":"executeStep","fileName":"TestStep.java","lineNumber":92},{"declaringClass":"io.cucumber.core.runner.TestStep","methodName":"run","fileName":"TestStep.java","lineNumber":64},{"declaringClass":"io.cucumber.core.runner.PickleStepTestStep","methodName":"run","fileName":"PickleStepTestStep.java","lineNumber":51},{"declaringClass":"io.cucumber.core.runner.TestCase","methodName":"run","fileName":"TestCase.java","lineNumber":104},{"declaringClass":"io.cucumber.core.runner.Runner","methodName":"runPickle","fileName":"Runner.java","lineNumber":73},{"declaringClass":"io.cucumber.junit.FeatureRunner","methodName":"runChild","fileName":"FeatureRunner.java","lineNumber":135},{"declaringClass":"io.cucumber.junit.FeatureRunner","methodName":"runChild","fileName":"FeatureRunner.java","lineNumber":27},{"declaringClass":"io.cucumber.junit.CucumberSerenityRunner","methodName":"runChild","fileName":"CucumberSerenityRunner.java","lineNumber":235},{"declaringClass":"io.cucumber.junit.CucumberSerenityRunner","methodName":"runChild","fileName":"CucumberSerenityRunner.java","lineNumber":54},{"declaringClass":"worker.org.gradle.process.internal.worker.GradleWorkerMain","methodName":"run","fileName":"GradleWorkerMain.java","lineNumber":69},{"declaringClass":"worker.org.gradle.process.internal.worker.GradleWorkerMain","methodName":"main","fileName":"GradleWorkerMain.java","lineNumber":74}],"rootCause":{"errorType":"org.openqa.selenium.TimeoutException","message":"Expected condition failed: waiting for By.cssSelector: .flex .login to be present (tried for 5 second(s) with 100 milliseconds interval)\nBuild info: version: \u00273.141.59\u0027, revision: \u0027e82be7d358\u0027, time: \u00272018-11-14T08:17:03\u0027\nSystem info: host: \u0027SWO059169593957\u0027, ip: \u0027192.168.68.53\u0027, os.name: \u0027Windows 10\u0027, os.arch: \u0027amd64\u0027, os.version: \u002710.0\u0027, java.version: \u00271.8.0_361\u0027\nDriver info: driver.version: unknown","stackTrace":[{"declaringClass":"org.example.Task.Iniciar","methodName":"performAs","fileName":"Iniciar.java","lineNumber":26},{"declaringClass":"org.example.stepdefinitions.StepDefinitions","methodName":"whenCrisUsingTheCredentialsOnRegister","fileName":"StepDefinitions.java","lineNumber":31},{"declaringClass":"io.cucumber.java.Invoker","methodName":"doInvoke","fileName":"Invoker.java","lineNumber":66},{"declaringClass":"io.cucumber.java.Invoker","methodName":"invoke","fileName":"Invoker.java","lineNumber":24},{"declaringClass":"io.cucumber.java.AbstractGlueDefinition","methodName":"invokeMethod","fileName":"AbstractGlueDefinition.java","lineNumber":47},{"declaringClass":"io.cucumber.java.JavaStepDefinition","methodName":"execute","fileName":"JavaStepDefinition.java","lineNumber":29},{"declaringClass":"io.cucumber.core.runner.CoreStepDefinition","methodName":"execute","fileName":"CoreStepDefinition.java","lineNumber":66},{"declaringClass":"io.cucumber.core.runner.PickleStepDefinitionMatch","methodName":"runStep","fileName":"PickleStepDefinitionMatch.java","lineNumber":63},{"declaringClass":"io.cucumber.core.runner.TestStep","methodName":"executeStep","fileName":"TestStep.java","lineNumber":92},{"declaringClass":"io.cucumber.core.runner.TestStep","methodName":"run","fileName":"TestStep.java","lineNumber":64},{"declaringClass":"io.cucumber.core.runner.PickleStepTestStep","methodName":"run","fileName":"PickleStepTestStep.java","lineNumber":51},{"declaringClass":"io.cucumber.core.runner.TestCase","methodName":"run","fileName":"TestCase.java","lineNumber":104},{"declaringClass":"io.cucumber.core.runner.Runner","methodName":"runPickle","fileName":"Runner.java","lineNumber":73},{"declaringClass":"io.cucumber.junit.FeatureRunner","methodName":"runChild","fileName":"FeatureRunner.java","lineNumber":135},{"declaringClass":"io.cucumber.junit.FeatureRunner","methodName":"runChild","fileName":"FeatureRunner.java","lineNumber":27},{"declaringClass":"io.cucumber.junit.CucumberSerenityRunner","methodName":"runChild","fileName":"CucumberSerenityRunner.java","lineNumber":235},{"declaringClass":"io.cucumber.junit.CucumberSerenityRunner","methodName":"runChild","fileName":"CucumberSerenityRunner.java","lineNumber":54},{"declaringClass":"worker.org.gradle.process.internal.worker.GradleWorkerMain","methodName":"run","fileName":"GradleWorkerMain.java","lineNumber":69},{"declaringClass":"worker.org.gradle.process.internal.worker.GradleWorkerMain","methodName":"main","fileName":"GradleWorkerMain.java","lineNumber":74}]}},"testFailureClassname":"net.thucydides.core.webdriver.exceptions.ElementShouldBePresentException","testFailureMessage":"Expected condition failed: waiting for By.cssSelector: .flex .login to be present (tried for 5 second(s) with 100 milliseconds interval)\nBuild info: version: \u00273.141.59\u0027, revision: \u0027e82be7d358\u0027, time: \u00272018-11-14T08:17:03\u0027\nSystem info: host: \u0027SWO059169593957\u0027, ip: \u0027192.168.68.53\u0027, os.name: \u0027Windows 10\u0027, os.arch: \u0027amd64\u0027, os.version: \u002710.0\u0027, java.version: \u00271.8.0_361\u0027\nDriver info: driver.version: unknown","testFailureSummary":"FAILURE;net.thucydides.core.webdriver.exceptions.ElementShouldBePresentException;Expected condition failed: waiting for By.cssSelector: .flex .login to be present (tried for 5 second(s) with 100 milliseconds interval)\nBuild info: version: \u00273.141.59\u0027, revision: \u0027e82be7d358\u0027, time: \u00272018-11-14T08:17:03\u0027\nSystem info: host: \u0027SWO059169593957\u0027, ip: \u0027192.168.68.53\u0027, os.name: \u0027Windows 10\u0027, os.arch: \u0027amd64\u0027, os.version: \u002710.0\u0027, java.version: \u00271.8.0_361\u0027\nDriver info: driver.version: unknown;Iniciar.java","projectKey":"","annotatedResult":"FAILURE","sessionId":"38e1989e779745418579a626b0b7db10","driver":"edge:actor","isManualTestingUpToDate":false,"manual":false,"testSource":"Cucumber","actors":[{"name":"actor","can":["browse the web"]}],"result":"FAILURE"}